pydantic_client/__init__.py
pydantic_client/async_client.py
pydantic_client/base.py
pydantic_client/cli.py
pydantic_client/decorators.py
pydantic_client/schema.py
pydantic_client/sync_client.py
pydantic_client/tools/__init__.py
pydantic_client/tools/agno.py
pydantic_client-2.0.6.dist-info/METADATA
pydantic_client-2.0.6.dist-info/WHEEL
pydantic_client-2.0.6.dist-info/entry_points.txt
pydantic_client-2.0.6.dist-info/licenses/LICENSE
pydantic_client-2.0.6.dist-info/RECORD
