Metadata-Version: 2.4
Name: pydantic-client
Version: 2.0.6
Summary: Http client base pydantic, with requests or aiohttp
Author-email: ponytailer <huangxiaohen2738@gmail.com>
License-File: LICENSE
Requires-Python: >=3.9
Requires-Dist: pydantic>=2.12.5
Requires-Dist: pyyaml>=6.0.3
Requires-Dist: requests
Requires-Dist: statsd>=4.0.1
Provides-Extra: aiohttp
Requires-Dist: aiohttp; extra == 'aiohttp'
Provides-Extra: all
Requires-Dist: aiohttp; extra == 'all'
Requires-Dist: httpx[http2]; extra == 'all'
Provides-Extra: httpx
Requires-Dist: httpx[http2]; extra == 'httpx'
